okome/__init__.py
okome/auth.py
okome/client.py
okome/util.py
okome_lib-1.1.2.dist-info/LICENSE
okome_lib-1.1.2.dist-info/METADATA
okome_lib-1.1.2.dist-info/WHEEL
okome_lib-1.1.2.dist-info/top_level.txt
okome_lib-1.1.2.dist-info/RECORD
