Metadata-Version: 2.1
Name: okome-lib
Version: 1.1.2
Summary: m.kuku.lu wrapper
Home-page: https://github.com/AntiTikTok/Okome-Lib
License-File: LICENSE
Requires-Dist: requests
